README.md
setup.py
bupytest/__init__.py
bupytest/__main__.py
bupytest/bupytest.py
bupytest/execution.py
bupytest.egg-info/PKG-INFO
bupytest.egg-info/SOURCES.txt
bupytest.egg-info/dependency_links.txt
bupytest.egg-info/entry_points.txt
bupytest.egg-info/requires.txt
bupytest.egg-info/top_level.txt