Metadata-Version: 2.1
Name: bupytest
Version: 1.3.1
Summary: Perform fast and detailed unit tests with BuPyTest.
Home-page: https://github.com/jaedsonpys/bupytest
Author: Jaedson Silva
Author-email: imunknowuser@protonmail.com
License: GPL-3.0
Project-URL: License, https://github.com/jaedsonpys/bupytest/blob/master/LICENSE
Project-URL: Documentation, https://github.com/jaedsonpys/bupytest/blob/master/README.md
Keywords: test,unittest,python,tdd,unit,sequential
Platform: UNKNOWN
